[
  {
    "ce_askprice": "671.05",
    "ce_askqty": "75",
    "ce_bidprice": "663.75",
    "ce_bidqty": "75",
    "ce_chng_in_oi": "-47175",
    "ce_iv": "82.98",
    "ce_ltp": "661.00",
    "ce_net_chng": "192.65",
    "ce_oi": "414675",
    "ce_volume": "2621",
    "pe_askprice": "221.50",
    "pe_askqty": "150",
    "pe_bidprice": "220.35",
    "pe_bidqty": "75",
    "pe_chng_in_oi": "58800",
    "pe_iv": "103.96",
    "pe_ltp": "220.25",
    "pe_net_chng": "-133.60",
    "pe_oi": "730800",
    "pe_volume": "17454",
    "spot_price": "8997",
    "strike_price": "8500",
    "time": "0952"
  },
  {
    "ce_askprice": "659.25",
    "ce_askqty": "75",
    "ce_bidprice": "654.65",
    "ce_bidqty": "75",
    "ce_chng_in_oi": "-47025",
    "ce_iv": "82.98",
    "ce_ltp": "660.65",
    "ce_net_chng": "192.30",
    "ce_oi": "414825",
    "ce_volume": "2640",
    "pe_askprice": "227.70",
    "pe_askqty": "75",
    "pe_bidprice": "226.75",
    "pe_bidqty": "75",
    "pe_chng_in_oi": "58125",
    "pe_iv": "103.96",
    "pe_ltp": "227.75",
    "pe_net_chng": "-126.10",
    "pe_oi": "730125",
    "pe_volume": "18016",
    "spot_price": "8987",
    "strike_price": "8500",
    "time": "0954"
  },
  {
    "ce_askprice": "654.25",
    "ce_askqty": "150",
    "ce_bidprice": "649.45",
    "ce_bidqty": "75",
    "ce_chng_in_oi": "-47325",
    "ce_iv": "82.98",
    "ce_ltp": "653.50",
    "ce_net_chng": "185.15",
    "ce_oi": "414525",
    "ce_volume": "2656",
    "pe_askprice": "228.40",
    "pe_askqty": "150",
    "pe_bidprice": "227.25",
    "pe_bidqty": "75",
    "pe_chng_in_oi": "60750",
    "pe_iv": "103.96",
    "pe_ltp": "228.30",
    "pe_net_chng": "-125.55",
    "pe_oi": "732750",
    "pe_volume": "18391",
    "spot_price": "8973",
    "strike_price": "8500",
    "time": "0957"
  },
  {
    "ce_askprice": "647.65",
    "ce_askqty": "75",
    "ce_bidprice": "643.35",
    "ce_bidqty": "150",
    "ce_chng_in_oi": "-49125",
    "ce_iv": "92.03",
    "ce_ltp": "644.05",
    "ce_net_chng": "175.70",
    "ce_oi": "412725",
    "ce_volume": "2745",
    "pe_askprice": "238.70",
    "pe_askqty": "150",
    "pe_bidprice": "237.90",
    "pe_bidqty": "75",
    "pe_chng_in_oi": "59175",
    "pe_iv": "105.42",
    "pe_ltp": "238.55",
    "pe_net_chng": "-115.30",
    "pe_oi": "731175",
    "pe_volume": "20269",
    "spot_price": "8940",
    "strike_price": "8500",
    "time": "1001"
  },
  {
    "ce_askprice": "643.65",
    "ce_askqty": "150",
    "ce_bidprice": "639.80",
    "ce_bidqty": "75",
    "ce_chng_in_oi": "-49125",
    "ce_iv": "89.99",
    "ce_ltp": "645.15",
    "ce_net_chng": "176.80",
    "ce_oi": "412725",
    "ce_volume": "2844",
    "pe_askprice": "239.60",
    "pe_askqty": "75",
    "pe_bidprice": "238.50",
    "pe_bidqty": "75",
    "pe_chng_in_oi": "64050",
    "pe_iv": "106.84",
    "pe_ltp": "237.85",
    "pe_net_chng": "-116.00",
    "pe_oi": "736050",
    "pe_volume": "21963",
    "spot_price": "8960",
    "strike_price": "8500",
    "time": "1004"
  },
  {
    "ce_askprice": "646.45",
    "ce_askqty": "75",
    "ce_bidprice": "641.80",
    "ce_bidqty": "75",
    "ce_chng_in_oi": "-51450",
    "ce_iv": "89.99",
    "ce_ltp": "643.00",
    "ce_net_chng": "174.65",
    "ce_oi": "410400",
    "ce_volume": "2939",
    "pe_askprice": "244.25",
    "pe_askqty": "75",
    "pe_bidprice": "243.20",
    "pe_bidqty": "75",
    "pe_chng_in_oi": "76950",
    "pe_iv": "106.84",
    "pe_ltp": "244.00",
    "pe_net_chng": "-109.85",
    "pe_oi": "748950",
    "pe_volume": "23743",
    "spot_price": "8925",
    "strike_price": "8500",
    "time": "1007"
  },
  {
    "ce_askprice": "625.00",
    "ce_askqty": "75",
    "ce_bidprice": "619.95",
    "ce_bidqty": "75",
    "ce_chng_in_oi": "-51450",
    "ce_iv": "89.99",
    "ce_ltp": "623.70",
    "ce_net_chng": "155.35",
    "ce_oi": "410400",
    "ce_volume": "2987",
    "pe_askprice": "257.00",
    "pe_askqty": "1125",
    "pe_bidprice": "256.15",
    "pe_bidqty": "75",
    "pe_chng_in_oi": "76950",
    "pe_iv": "106.84",
    "pe_ltp": "255.55",
    "pe_net_chng": "-98.30",
    "pe_oi": "748950",
    "pe_volume": "25084",
    "spot_price": "8901",
    "strike_price": "8500",
    "time": "1010"
  },
  {
    "ce_askprice": "648.70",
    "ce_askqty": "75",
    "ce_bidprice": "642.95",
    "ce_bidqty": "75",
    "ce_chng_in_oi": "-50100",
    "ce_iv": "94.41",
    "ce_ltp": "644.80",
    "ce_net_chng": "176.45",
    "ce_oi": "411750",
    "ce_volume": "3129",
    "pe_askprice": "238.80",
    "pe_askqty": "75",
    "pe_bidprice": "237.55",
    "pe_bidqty": "150",
    "pe_chng_in_oi": "74250",
    "pe_iv": "103.53",
    "pe_ltp": "237.85",
    "pe_net_chng": "-116.00",
    "pe_oi": "746250",
    "pe_volume": "28971",
    "spot_price": "8947",
    "strike_price": "8500",
    "time": "1013"
  },
  {
    "ce_askprice": "573.15",
    "ce_askqty": "150",
    "ce_bidprice": "567.05",
    "ce_bidqty": "75",
    "ce_chng_in_oi": "-50100",
    "ce_iv": "94.41",
    "ce_ltp": "575.00",
    "ce_net_chng": "106.65",
    "ce_oi": "411750",
    "ce_volume": "3231",
    "pe_askprice": "283.55",
    "pe_askqty": "75",
    "pe_bidprice": "281.20",
    "pe_bidqty": "300",
    "pe_chng_in_oi": "74250",
    "pe_iv": "103.53",
    "pe_ltp": "281.20",
    "pe_net_chng": "-72.65",
    "pe_oi": "746250",
    "pe_volume": "30808",
    "spot_price": "8831",
    "strike_price": "8500",
    "time": "1016"
  },
  {
    "ce_askprice": "594.00",
    "ce_askqty": "75",
    "ce_bidprice": "590.00",
    "ce_bidqty": "150",
    "ce_chng_in_oi": "-50100",
    "ce_iv": "94.41",
    "ce_ltp": "590.05",
    "ce_net_chng": "121.70",
    "ce_oi": "411750",
    "ce_volume": "3408",
    "pe_askprice": "281.40",
    "pe_askqty": "225",
    "pe_bidprice": "280.00",
    "pe_bidqty": "675",
    "pe_chng_in_oi": "81900",
    "pe_iv": "103.53",
    "pe_ltp": "280.00",
    "pe_net_chng": "-73.85",
    "pe_oi": "753900",
    "pe_volume": "33836",
    "spot_price": "8835",
    "strike_price": "8500",
    "time": "1019"
  },
  {
    "ce_askprice": "597.05",
    "ce_askqty": "75",
    "ce_bidprice": "589.45",
    "ce_bidqty": "75",
    "ce_chng_in_oi": "-40350",
    "ce_iv": "97.37",
    "ce_ltp": "591.20",
    "ce_net_chng": "122.85",
    "ce_oi": "421500",
    "ce_volume": "3753",
    "pe_askprice": "284.20",
    "pe_askqty": "75",
    "pe_bidprice": "282.10",
    "pe_bidqty": "450",
    "pe_chng_in_oi": "68475",
    "pe_iv": "108.57",
    "pe_ltp": "284.80",
    "pe_net_chng": "-69.05",
    "pe_oi": "740475",
    "pe_volume": "38161",
    "spot_price": "8833",
    "strike_price": "8500",
    "time": "1022"
  },
  {
    "ce_askprice": "589.65",
    "ce_askqty": "150",
    "ce_bidprice": "583.35",
    "ce_bidqty": "75",
    "ce_chng_in_oi": "-40350",
    "ce_iv": "97.37",
    "ce_ltp": "588.40",
    "ce_net_chng": "120.05",
    "ce_oi": "421500",
    "ce_volume": "3791",
    "pe_askprice": "284.25",
    "pe_askqty": "75",
    "pe_bidprice": "283.00",
    "pe_bidqty": "75",
    "pe_chng_in_oi": "68475",
    "pe_iv": "108.57",
    "pe_ltp": "284.20",
    "pe_net_chng": "-69.65",
    "pe_oi": "740475",
    "pe_volume": "39865",
    "spot_price": "8836",
    "strike_price": "8500",
    "time": "1025"
  },
  {
    "ce_askprice": "621.60",
    "ce_askqty": "150",
    "ce_bidprice": "614.30",
    "ce_bidqty": "75",
    "ce_chng_in_oi": "-40725",
    "ce_iv": "97.37",
    "ce_ltp": "626.60",
    "ce_net_chng": "158.25",
    "ce_oi": "421125",
    "ce_volume": "3864",
    "pe_askprice": "267.00",
    "pe_askqty": "225",
    "pe_bidprice": "265.40",
    "pe_bidqty": "75",
    "pe_chng_in_oi": "61575",
    "pe_iv": "108.57",
    "pe_ltp": "265.40",
    "pe_net_chng": "-88.45",
    "pe_oi": "733575",
    "pe_volume": "41715",
    "spot_price": "8887",
    "strike_price": "8500",
    "time": "1028"
  },
  {
    "ce_askprice": "617.70",
    "ce_askqty": "75",
    "ce_bidprice": "611.70",
    "ce_bidqty": "75",
    "ce_chng_in_oi": "-41925",
    "ce_iv": "97.37",
    "ce_ltp": "609.00",
    "ce_net_chng": "140.65",
    "ce_oi": "419925",
    "ce_volume": "3892",
    "pe_askprice": "272.05",
    "pe_askqty": "75",
    "pe_bidprice": "271.00",
    "pe_bidqty": "375",
    "pe_chng_in_oi": "51675",
    "pe_iv": "108.57",
    "pe_ltp": "272.20",
    "pe_net_chng": "-81.65",
    "pe_oi": "723675",
    "pe_volume": "42551",
    "spot_price": "8874",
    "strike_price": "8500",
    "time": "1031"
  },
  {
    "ce_askprice": "598.30",
    "ce_askqty": "300",
    "ce_bidprice": "592.10",
    "ce_bidqty": "375",
    "ce_chng_in_oi": "-41250",
    "ce_iv": "97.31",
    "ce_ltp": "601.20",
    "ce_net_chng": "132.85",
    "ce_oi": "420600",
    "ce_volume": "3966",
    "pe_askprice": "289.90",
    "pe_askqty": "75",
    "pe_bidprice": "288.65",
    "pe_bidqty": "75",
    "pe_chng_in_oi": "57525",
    "pe_iv": "109.48",
    "pe_ltp": "289.90",
    "pe_net_chng": "-63.95",
    "pe_oi": "729525",
    "pe_volume": "43866",
    "spot_price": "8855",
    "strike_price": "8500",
    "time": "1033"
  },
  {
    "ce_askprice": "576.70",
    "ce_askqty": "75",
    "ce_bidprice": "570.35",
    "ce_bidqty": "150",
    "ce_chng_in_oi": "-42450",
    "ce_iv": "97.31",
    "ce_ltp": "567.40",
    "ce_net_chng": "99.05",
    "ce_oi": "419400",
    "ce_volume": "4041",
    "pe_askprice": "299.35",
    "pe_askqty": "75",
    "pe_bidprice": "298.20",
    "pe_bidqty": "75",
    "pe_chng_in_oi": "62025",
    "pe_iv": "109.48",
    "pe_ltp": "299.40",
    "pe_net_chng": "-54.45",
    "pe_oi": "734025",
    "pe_volume": "46613",
    "spot_price": "8812",
    "strike_price": "8500",
    "time": "1037"
  },
  {
    "ce_askprice": "580.90",
    "ce_askqty": "150",
    "ce_bidprice": "574.45",
    "ce_bidqty": "75",
    "ce_chng_in_oi": "-42450",
    "ce_iv": "97.31",
    "ce_ltp": "579.75",
    "ce_net_chng": "111.40",
    "ce_oi": "419400",
    "ce_volume": "4098",
    "pe_askprice": "302.65",
    "pe_askqty": "225",
    "pe_bidprice": "301.10",
    "pe_bidqty": "150",
    "pe_chng_in_oi": "62025",
    "pe_iv": "109.48",
    "pe_ltp": "302.20",
    "pe_net_chng": "-51.65",
    "pe_oi": "734025",
    "pe_volume": "47665",
    "spot_price": "8810",
    "strike_price": "8500",
    "time": "1040"
  },
  {
    "ce_askprice": "593.95",
    "ce_askqty": "75",
    "ce_bidprice": "586.95",
    "ce_bidqty": "150",
    "ce_chng_in_oi": "-41775",
    "ce_iv": "97.48",
    "ce_ltp": "588.60",
    "ce_net_chng": "120.25",
    "ce_oi": "420075",
    "ce_volume": "4119",
    "pe_askprice": "292.80",
    "pe_askqty": "825",
    "pe_bidprice": "291.10",
    "pe_bidqty": "450",
    "pe_chng_in_oi": "68400",
    "pe_iv": "110.20",
    "pe_ltp": "291.10",
    "pe_net_chng": "-62.75",
    "pe_oi": "740400",
    "pe_volume": "48392",
    "spot_price": "8840",
    "strike_price": "8500",
    "time": "1043"
  },
  {
    "ce_askprice": "558.20",
    "ce_askqty": "375",
    "ce_bidprice": "551.20",
    "ce_bidqty": "150",
    "ce_chng_in_oi": "-42000",
    "ce_iv": "97.48",
    "ce_ltp": "558.05",
    "ce_net_chng": "89.70",
    "ce_oi": "419850",
    "ce_volume": "4196",
    "pe_askprice": "317.95",
    "pe_askqty": "750",
    "pe_bidprice": "316.25",
    "pe_bidqty": "150",
    "pe_chng_in_oi": "72075",
    "pe_iv": "110.20",
    "pe_ltp": "318.00",
    "pe_net_chng": "-35.85",
    "pe_oi": "744075",
    "pe_volume": "50215",
    "spot_price": "8780",
    "strike_price": "8500",
    "time": "1046"
  },
  {
    "ce_askprice": "552.70",
    "ce_askqty": "150",
    "ce_bidprice": "547.10",
    "ce_bidqty": "75",
    "ce_chng_in_oi": "-41550",
    "ce_iv": "97.48",
    "ce_ltp": "548.55",
    "ce_net_chng": "80.20",
    "ce_oi": "420300",
    "ce_volume": "4566",
    "pe_askprice": "322.95",
    "pe_askqty": "150",
    "pe_bidprice": "321.30",
    "pe_bidqty": "75",
    "pe_chng_in_oi": "80325",
    "pe_iv": "110.20",
    "pe_ltp": "322.75",
    "pe_net_chng": "-31.10",
    "pe_oi": "752325",
    "pe_volume": "51836",
    "spot_price": "8760",
    "strike_price": "8500",
    "time": "1049"
  },
  {
    "ce_askprice": "569.55",
    "ce_askqty": "75",
    "ce_bidprice": "562.00",
    "ce_bidqty": "225",
    "ce_chng_in_oi": "-40425",
    "ce_iv": "99.16",
    "ce_ltp": "562.65",
    "ce_net_chng": "94.30",
    "ce_oi": "421425",
    "ce_volume": "4734",
    "pe_askprice": "316.55",
    "pe_askqty": "150",
    "pe_bidprice": "314.85",
    "pe_bidqty": "150",
    "pe_chng_in_oi": "79350",
    "pe_iv": "109.62",
    "pe_ltp": "314.75",
    "pe_net_chng": "-39.10",
    "pe_oi": "751350",
    "pe_volume": "53115",
    "spot_price": "8761",
    "strike_price": "8500",
    "time": "1051"
  },
  {
    "ce_askprice": "557.40",
    "ce_askqty": "75",
    "ce_bidprice": "551.20",
    "ce_bidqty": "150",
    "ce_chng_in_oi": "-40500",
    "ce_iv": "99.16",
    "ce_ltp": "547.80",
    "ce_net_chng": "79.45",
    "ce_oi": "421350",
    "ce_volume": "4753",
    "pe_askprice": "319.00",
    "pe_askqty": "75",
    "pe_bidprice": "318.00",
    "pe_bidqty": "150",
    "pe_chng_in_oi": "75000",
    "pe_iv": "109.62",
    "pe_ltp": "318.10",
    "pe_net_chng": "-35.75",
    "pe_oi": "747000",
    "pe_volume": "53690",
    "spot_price": "8759",
    "strike_price": "8500",
    "time": "1054"
  },
  {
    "ce_askprice": "522.70",
    "ce_askqty": "75",
    "ce_bidprice": "521.20",
    "ce_bidqty": "75",
    "ce_chng_in_oi": "-41250",
    "ce_iv": "99.16",
    "ce_ltp": "522.75",
    "ce_net_chng": "54.40",
    "ce_oi": "420600",
    "ce_volume": "5021",
    "pe_askprice": "332.80",
    "pe_askqty": "225",
    "pe_bidprice": "331.50",
    "pe_bidqty": "75",
    "pe_chng_in_oi": "70275",
    "pe_iv": "109.62",
    "pe_ltp": "332.80",
    "pe_net_chng": "-21.05",
    "pe_oi": "742275",
    "pe_volume": "55837",
    "spot_price": "8703",
    "strike_price": "8500",
    "time": "1058"
  },
  {
    "ce_askprice": "496.65",
    "ce_askqty": "75",
    "ce_bidprice": "493.00",
    "ce_bidqty": "150",
    "ce_chng_in_oi": "-43575",
    "ce_iv": "99.16",
    "ce_ltp": "498.00",
    "ce_net_chng": "29.65",
    "ce_oi": "418275",
    "ce_volume": "5280",
    "pe_askprice": "357.95",
    "pe_askqty": "75",
    "pe_bidprice": "356.65",
    "pe_bidqty": "75",
    "pe_chng_in_oi": "59100",
    "pe_iv": "109.62",
    "pe_ltp": "357.30",
    "pe_net_chng": "3.45",
    "pe_oi": "731100",
    "pe_volume": "58728",
    "spot_price": "8662",
    "strike_price": "8500",
    "time": "1101"
  },
  {
    "ce_askprice": "497.90",
    "ce_askqty": "150",
    "ce_bidprice": "494.00",
    "ce_bidqty": "75",
    "ce_chng_in_oi": "-43575",
    "ce_iv": "101.25",
    "ce_ltp": "497.85",
    "ce_net_chng": "29.50",
    "ce_oi": "418275",
    "ce_volume": "5336",
    "pe_askprice": "351.90",
    "pe_askqty": "75",
    "pe_bidprice": "350.25",
    "pe_bidqty": "75",
    "pe_chng_in_oi": "59100",
    "pe_iv": "109.66",
    "pe_ltp": "350.95",
    "pe_net_chng": "-2.90",
    "pe_oi": "731100",
    "pe_volume": "59977",
    "spot_price": "8654",
    "strike_price": "8500",
    "time": "1103"
  },
  {
    "ce_askprice": "530.85",
    "ce_askqty": "150",
    "ce_bidprice": "525.20",
    "ce_bidqty": "300",
    "ce_chng_in_oi": "-37125",
    "ce_iv": "101.25",
    "ce_ltp": "527.35",
    "ce_net_chng": "59.00",
    "ce_oi": "424725",
    "ce_volume": "5503",
    "pe_askprice": "330.00",
    "pe_askqty": "75",
    "pe_bidprice": "328.80",
    "pe_bidqty": "75",
    "pe_chng_in_oi": "66825",
    "pe_iv": "109.66",
    "pe_ltp": "329.75",
    "pe_net_chng": "-24.10",
    "pe_oi": "738825",
    "pe_volume": "62537",
    "spot_price": "8726",
    "strike_price": "8500",
    "time": "1107"
  },
  {
    "ce_askprice": "509.80",
    "ce_askqty": "75",
    "ce_bidprice": "503.00",
    "ce_bidqty": "75",
    "ce_chng_in_oi": "-35925",
    "ce_iv": "101.25",
    "ce_ltp": "507.30",
    "ce_net_chng": "38.95",
    "ce_oi": "425925",
    "ce_volume": "5518",
    "pe_askprice": "356.40",
    "pe_askqty": "75",
    "pe_bidprice": "354.90",
    "pe_bidqty": "300",
    "pe_chng_in_oi": "69375",
    "pe_iv": "109.66",
    "pe_ltp": "356.00",
    "pe_net_chng": "2.15",
    "pe_oi": "741375",
    "pe_volume": "63307",
    "spot_price": "8675",
    "strike_price": "8500",
    "time": "1110"
  },
  {
    "ce_askprice": "496.60",
    "ce_askqty": "75",
    "ce_bidprice": "493.40",
    "ce_bidqty": "75",
    "ce_chng_in_oi": "-35775",
    "ce_iv": "101.25",
    "ce_ltp": "493.50",
    "ce_net_chng": "25.15",
    "ce_oi": "426075",
    "ce_volume": "5593",
    "pe_askprice": "363.65",
    "pe_askqty": "75",
    "pe_bidprice": "362.40",
    "pe_bidqty": "75",
    "pe_chng_in_oi": "71325",
    "pe_iv": "109.66",
    "pe_ltp": "362.45",
    "pe_net_chng": "8.60",
    "pe_oi": "743325",
    "pe_volume": "64822",
    "spot_price": "8650",
    "strike_price": "8500",
    "time": "1113"
  },
  {
    "ce_askprice": "459.50",
    "ce_askqty": "75",
    "ce_bidprice": "456.95",
    "ce_bidqty": "75",
    "ce_chng_in_oi": "-35475",
    "ce_iv": "101.25",
    "ce_ltp": "458.10",
    "ce_net_chng": "-10.25",
    "ce_oi": "426375",
    "ce_volume": "6052",
    "pe_askprice": "381.55",
    "pe_askqty": "75",
    "pe_bidprice": "379.70",
    "pe_bidqty": "150",
    "pe_chng_in_oi": "71475",
    "pe_iv": "109.66",
    "pe_ltp": "380.00",
    "pe_net_chng": "26.15",
    "pe_oi": "743475",
    "pe_volume": "67532",
    "spot_price": "8584",
    "strike_price": "8500",
    "time": "1116"
  },
  {
    "ce_askprice": "441.70",
    "ce_askqty": "75",
    "ce_bidprice": "437.10",
    "ce_bidqty": "75",
    "ce_chng_in_oi": "-22125",
    "ce_iv": "101.25",
    "ce_ltp": "440.00",
    "ce_net_chng": "-28.35",
    "ce_oi": "439725",
    "ce_volume": "6467",
    "pe_askprice": "391.60",
    "pe_askqty": "75",
    "pe_bidprice": "389.95",
    "pe_bidqty": "525",
    "pe_chng_in_oi": "80700",
    "pe_iv": "109.66",
    "pe_ltp": "390.20",
    "pe_net_chng": "36.35",
    "pe_oi": "752700",
    "pe_volume": "69270",
    "spot_price": "8563",
    "strike_price": "8500",
    "time": "1118"
  },
  {
    "ce_askprice": "429.65",
    "ce_askqty": "150",
    "ce_bidprice": "426.75",
    "ce_bidqty": "75",
    "ce_chng_in_oi": "-5100",
    "ce_iv": "101.25",
    "ce_ltp": "428.70",
    "ce_net_chng": "-39.65",
    "ce_oi": "456750",
    "ce_volume": "6752",
    "pe_askprice": "393.55",
    "pe_askqty": "75",
    "pe_bidprice": "392.00",
    "pe_bidqty": "225",
    "pe_chng_in_oi": "89700",
    "pe_iv": "109.66",
    "pe_ltp": "393.75",
    "pe_net_chng": "39.90",
    "pe_oi": "761700",
    "pe_volume": "70259",
    "spot_price": "8554",
    "strike_price": "8500",
    "time": "1121"
  },
  {
    "ce_askprice": "444.00",
    "ce_askqty": "75",
    "ce_bidprice": "441.35",
    "ce_bidqty": "75",
    "ce_chng_in_oi": "-75",
    "ce_iv": "101.25",
    "ce_ltp": "442.50",
    "ce_net_chng": "-25.85",
    "ce_oi": "461775",
    "ce_volume": "7130",
    "pe_askprice": "386.35",
    "pe_askqty": "150",
    "pe_bidprice": "384.65",
    "pe_bidqty": "75",
    "pe_chng_in_oi": "83775",
    "pe_iv": "109.66",
    "pe_ltp": "385.70",
    "pe_net_chng": "31.85",
    "pe_oi": "755775",
    "pe_volume": "71290",
    "spot_price": "8581",
    "strike_price": "8500",
    "time": "1124"
  },
  {
    "ce_askprice": "455.75",
    "ce_askqty": "375",
    "ce_bidprice": "451.90",
    "ce_bidqty": "75",
    "ce_chng_in_oi": "1725",
    "ce_iv": "101.25",
    "ce_ltp": "455.85",
    "ce_net_chng": "-12.50",
    "ce_oi": "463575",
    "ce_volume": "7314",
    "pe_askprice": "371.45",
    "pe_askqty": "75",
    "pe_bidprice": "370.00",
    "pe_bidqty": "450",
    "pe_chng_in_oi": "89025",
    "pe_iv": "109.66",
    "pe_ltp": "371.00",
    "pe_net_chng": "17.15",
    "pe_oi": "761025",
    "pe_volume": "71889",
    "spot_price": "8608",
    "strike_price": "8500",
    "time": "1127"
  },
  {
    "ce_askprice": "479.95",
    "ce_askqty": "150",
    "ce_bidprice": "475.75",
    "ce_bidqty": "150",
    "ce_chng_in_oi": "-900",
    "ce_iv": "101.25",
    "ce_ltp": "478.65",
    "ce_net_chng": "10.30",
    "ce_oi": "460950",
    "ce_volume": "8069",
    "pe_askprice": "333.20",
    "pe_askqty": "150",
    "pe_bidprice": "331.10",
    "pe_bidqty": "150",
    "pe_chng_in_oi": "85125",
    "pe_iv": "109.66",
    "pe_ltp": "330.60",
    "pe_net_chng": "-23.25",
    "pe_oi": "757125",
    "pe_volume": "74576",
    "spot_price": "8668",
    "strike_price": "8500",
    "time": "1130"
  },
  {
    "ce_askprice": "480.00",
    "ce_askqty": "75",
    "ce_bidprice": "478.20",
    "ce_bidqty": "75",
    "ce_chng_in_oi": "-",
    "ce_iv": "101.25",
    "ce_ltp": "480.00",
    "ce_net_chng": "11.65",
    "ce_oi": "461850",
    "ce_volume": "8275",
    "pe_askprice": "344.00",
    "pe_askqty": "75",
    "pe_bidprice": "343.10",
    "pe_bidqty": "75",
    "pe_chng_in_oi": "96975",
    "pe_iv": "109.66",
    "pe_ltp": "343.20",
    "pe_net_chng": "-10.65",
    "pe_oi": "768975",
    "pe_volume": "75852",
    "spot_price": "8643",
    "strike_price": "8500",
    "time": "1134"
  },
  {
    "ce_askprice": "464.25",
    "ce_askqty": "150",
    "ce_bidprice": "461.05",
    "ce_bidqty": "75",
    "ce_chng_in_oi": "1875",
    "ce_iv": "101.25",
    "ce_ltp": "465.05",
    "ce_net_chng": "-3.30",
    "ce_oi": "463725",
    "ce_volume": "8457",
    "pe_askprice": "354.45",
    "pe_askqty": "75",
    "pe_bidprice": "352.95",
    "pe_bidqty": "75",
    "pe_chng_in_oi": "109275",
    "pe_iv": "109.66",
    "pe_ltp": "353.90",
    "pe_net_chng": "0.05",
    "pe_oi": "781275",
    "pe_volume": "77047",
    "spot_price": "8626",
    "strike_price": "8500",
    "time": "1137"
  },
  {
    "ce_askprice": "483.15",
    "ce_askqty": "75",
    "ce_bidprice": "479.00",
    "ce_bidqty": "225",
    "ce_chng_in_oi": "1875",
    "ce_iv": "101.25",
    "ce_ltp": "479.00",
    "ce_net_chng": "10.65",
    "ce_oi": "463725",
    "ce_volume": "8512",
    "pe_askprice": "343.00",
    "pe_askqty": "150",
    "pe_bidprice": "341.50",
    "pe_bidqty": "75",
    "pe_chng_in_oi": "109275",
    "pe_iv": "109.66",
    "pe_ltp": "342.80",
    "pe_net_chng": "-11.05",
    "pe_oi": "781275",
    "pe_volume": "77551",
    "spot_price": "8652",
    "strike_price": "8500",
    "time": "1140"
  },
  {
    "ce_askprice": "484.95",
    "ce_askqty": "75",
    "ce_bidprice": "481.15",
    "ce_bidqty": "225",
    "ce_chng_in_oi": "2625",
    "ce_iv": "101.25",
    "ce_ltp": "483.80",
    "ce_net_chng": "15.45",
    "ce_oi": "464475",
    "ce_volume": "8558",
    "pe_askprice": "345.00",
    "pe_askqty": "225",
    "pe_bidprice": "343.90",
    "pe_bidqty": "75",
    "pe_chng_in_oi": "111975",
    "pe_iv": "109.66",
    "pe_ltp": "345.30",
    "pe_net_chng": "-8.55",
    "pe_oi": "783975",
    "pe_volume": "77961",
    "spot_price": "8652",
    "strike_price": "8500",
    "time": "1143"
  },
  {
    "ce_askprice": "484.90",
    "ce_askqty": "150",
    "ce_bidprice": "480.80",
    "ce_bidqty": "375",
    "ce_chng_in_oi": "2400",
    "ce_iv": "101.25",
    "ce_ltp": "484.90",
    "ce_net_chng": "16.55",
    "ce_oi": "464250",
    "ce_volume": "8641",
    "pe_askprice": "349.50",
    "pe_askqty": "75",
    "pe_bidprice": "348.00",
    "pe_bidqty": "300",
    "pe_chng_in_oi": "108525",
    "pe_iv": "109.66",
    "pe_ltp": "348.40",
    "pe_net_chng": "-5.45",
    "pe_oi": "780525",
    "pe_volume": "78614",
    "spot_price": "8651",
    "strike_price": "8500",
    "time": "1146"
  },
  {
    "ce_askprice": "471.60",
    "ce_askqty": "150",
    "ce_bidprice": "468.20",
    "ce_bidqty": "75",
    "ce_chng_in_oi": "2400",
    "ce_iv": "101.25",
    "ce_ltp": "478.65",
    "ce_net_chng": "10.30",
    "ce_oi": "464250",
    "ce_volume": "8740",
    "pe_askprice": "355.00",
    "pe_askqty": "600",
    "pe_bidprice": "354.20",
    "pe_bidqty": "75",
    "pe_chng_in_oi": "108525",
    "pe_iv": "109.66",
    "pe_ltp": "354.00",
    "pe_net_chng": "0.15",
    "pe_oi": "780525",
    "pe_volume": "78948",
    "spot_price": "8645",
    "strike_price": "8500",
    "time": "1149"
  },
  {
    "ce_askprice": "467.05",
    "ce_askqty": "150",
    "ce_bidprice": "462.50",
    "ce_bidqty": "375",
    "ce_chng_in_oi": "3975",
    "ce_iv": "101.25",
    "ce_ltp": "467.10",
    "ce_net_chng": "-1.25",
    "ce_oi": "465825",
    "ce_volume": "8959",
    "pe_askprice": "354.05",
    "pe_askqty": "75",
    "pe_bidprice": "352.40",
    "pe_bidqty": "75",
    "pe_chng_in_oi": "114750",
    "pe_iv": "109.66",
    "pe_ltp": "353.15",
    "pe_net_chng": "-0.70",
    "pe_oi": "786750",
    "pe_volume": "80586",
    "spot_price": "8640",
    "strike_price": "8500",
    "time": "1153"
  },
  {
    "ce_askprice": "483.55",
    "ce_askqty": "75",
    "ce_bidprice": "480.30",
    "ce_bidqty": "150",
    "ce_chng_in_oi": "5625",
    "ce_iv": "101.25",
    "ce_ltp": "480.10",
    "ce_net_chng": "11.75",
    "ce_oi": "467475",
    "ce_volume": "9026",
    "pe_askprice": "344.40",
    "pe_askqty": "75",
    "pe_bidprice": "343.40",
    "pe_bidqty": "75",
    "pe_chng_in_oi": "111075",
    "pe_iv": "109.66",
    "pe_ltp": "344.30",
    "pe_net_chng": "-9.55",
    "pe_oi": "783075",
    "pe_volume": "81225",
    "spot_price": "8646",
    "strike_price": "8500",
    "time": "1156"
  },
  {
    "ce_askprice": "489.95",
    "ce_askqty": "75",
    "ce_bidprice": "485.55",
    "ce_bidqty": "225",
    "ce_chng_in_oi": "5625",
    "ce_iv": "101.25",
    "ce_ltp": "488.00",
    "ce_net_chng": "19.65",
    "ce_oi": "467475",
    "ce_volume": "9084",
    "pe_askprice": "347.30",
    "pe_askqty": "75",
    "pe_bidprice": "345.85",
    "pe_bidqty": "75",
    "pe_chng_in_oi": "111075",
    "pe_iv": "109.66",
    "pe_ltp": "345.60",
    "pe_net_chng": "-8.25",
    "pe_oi": "783075",
    "pe_volume": "81698",
    "spot_price": "8655",
    "strike_price": "8500",
    "time": "1158"
  },
  {
    "ce_askprice": "534.50",
    "ce_askqty": "75",
    "ce_bidprice": "532.65",
    "ce_bidqty": "225",
    "ce_chng_in_oi": "8250",
    "ce_iv": "101.25",
    "ce_ltp": "532.65",
    "ce_net_chng": "64.30",
    "ce_oi": "470100",
    "ce_volume": "9436",
    "pe_askprice": "311.20",
    "pe_askqty": "75",
    "pe_bidprice": "310.00",
    "pe_bidqty": "2850",
    "pe_chng_in_oi": "114150",
    "pe_iv": "109.66",
    "pe_ltp": "310.65",
    "pe_net_chng": "-43.20",
    "pe_oi": "786150",
    "pe_volume": "83670",
    "spot_price": "8730",
    "strike_price": "8500",
    "time": "1201"
  },
  {
    "ce_askprice": "526.15",
    "ce_askqty": "75",
    "ce_bidprice": "523.90",
    "ce_bidqty": "75",
    "ce_chng_in_oi": "8250",
    "ce_iv": "101.25",
    "ce_ltp": "524.00",
    "ce_net_chng": "55.65",
    "ce_oi": "470100",
    "ce_volume": "9569",
    "pe_askprice": "314.45",
    "pe_askqty": "75",
    "pe_bidprice": "312.90",
    "pe_bidqty": "75",
    "pe_chng_in_oi": "114150",
    "pe_iv": "109.66",
    "pe_ltp": "314.70",
    "pe_net_chng": "-39.15",
    "pe_oi": "786150",
    "pe_volume": "84551",
    "spot_price": "8726",
    "strike_price": "8500",
    "time": "1204"
  },
  {
    "ce_askprice": "518.85",
    "ce_askqty": "225",
    "ce_bidprice": "515.05",
    "ce_bidqty": "150",
    "ce_chng_in_oi": "5550",
    "ce_iv": "101.25",
    "ce_ltp": "523.45",
    "ce_net_chng": "55.10",
    "ce_oi": "467400",
    "ce_volume": "9650",
    "pe_askprice": "324.55",
    "pe_askqty": "225",
    "pe_bidprice": "322.80",
    "pe_bidqty": "75",
    "pe_chng_in_oi": "123825",
    "pe_iv": "109.66",
    "pe_ltp": "324.55",
    "pe_net_chng": "-29.30",
    "pe_oi": "795825",
    "pe_volume": "85535",
    "spot_price": "8704",
    "strike_price": "8500",
    "time": "1208"
  },
  {
    "ce_askprice": "504.45",
    "ce_askqty": "150",
    "ce_bidprice": "500.20",
    "ce_bidqty": "75",
    "ce_chng_in_oi": "4800",
    "ce_iv": "101.25",
    "ce_ltp": "504.25",
    "ce_net_chng": "35.90",
    "ce_oi": "466650",
    "ce_volume": "9722",
    "pe_askprice": "331.30",
    "pe_askqty": "75",
    "pe_bidprice": "329.85",
    "pe_bidqty": "225",
    "pe_chng_in_oi": "131925",
    "pe_iv": "109.66",
    "pe_ltp": "330.00",
    "pe_net_chng": "-23.85",
    "pe_oi": "803925",
    "pe_volume": "86155",
    "spot_price": "8681",
    "strike_price": "8500",
    "time": "1210"
  },
  {
    "ce_askprice": "502.80",
    "ce_askqty": "75",
    "ce_bidprice": "498.65",
    "ce_bidqty": "75",
    "ce_chng_in_oi": "5475",
    "ce_iv": "101.25",
    "ce_ltp": "500.60",
    "ce_net_chng": "32.25",
    "ce_oi": "467325",
    "ce_volume": "9748",
    "pe_askprice": "336.05",
    "pe_askqty": "300",
    "pe_bidprice": "335.00",
    "pe_bidqty": "300",
    "pe_chng_in_oi": "133950",
    "pe_iv": "109.66",
    "pe_ltp": "336.00",
    "pe_net_chng": "-17.85",
    "pe_oi": "805950",
    "pe_volume": "86505",
    "spot_price": "8678",
    "strike_price": "8500",
    "time": "1213"
  },
  {
    "ce_askprice": "521.10",
    "ce_askqty": "525",
    "ce_bidprice": "516.40",
    "ce_bidqty": "75",
    "ce_chng_in_oi": "5100",
    "ce_iv": "101.25",
    "ce_ltp": "520.80",
    "ce_net_chng": "52.45",
    "ce_oi": "466950",
    "ce_volume": "9782",
    "pe_askprice": "319.80",
    "pe_askqty": "75",
    "pe_bidprice": "318.70",
    "pe_bidqty": "75",
    "pe_chng_in_oi": "137100",
    "pe_iv": "109.66",
    "pe_ltp": "319.75",
    "pe_net_chng": "-34.10",
    "pe_oi": "809100",
    "pe_volume": "87300",
    "spot_price": "8713",
    "strike_price": "8500",
    "time": "1217"
  },
  {
    "ce_askprice": "486.10",
    "ce_askqty": "75",
    "ce_bidprice": "482.80",
    "ce_bidqty": "75",
    "ce_chng_in_oi": "7500",
    "ce_iv": "101.25",
    "ce_ltp": "480.70",
    "ce_net_chng": "12.35",
    "ce_oi": "469350",
    "ce_volume": "10015",
    "pe_askprice": "346.70",
    "pe_askqty": "150",
    "pe_bidprice": "345.15",
    "pe_bidqty": "75",
    "pe_chng_in_oi": "139725",
    "pe_iv": "109.66",
    "pe_ltp": "346.25",
    "pe_net_chng": "-7.60",
    "pe_oi": "811725",
    "pe_volume": "88510",
    "spot_price": "8672",
    "strike_price": "8500",
    "time": "1219"
  },
  {
    "ce_askprice": "505.80",
    "ce_askqty": "300",
    "ce_bidprice": "501.45",
    "ce_bidqty": "75",
    "ce_chng_in_oi": "7500",
    "ce_iv": "101.25",
    "ce_ltp": "504.60",
    "ce_net_chng": "36.25",
    "ce_oi": "469350",
    "ce_volume": "10047",
    "pe_askprice": "330.95",
    "pe_askqty": "75",
    "pe_bidprice": "330.00",
    "pe_bidqty": "375",
    "pe_chng_in_oi": "139725",
    "pe_iv": "109.66",
    "pe_ltp": "330.50",
    "pe_net_chng": "-23.35",
    "pe_oi": "811725",
    "pe_volume": "88863",
    "spot_price": "8700",
    "strike_price": "8500",
    "time": "1222"
  },
  {
    "ce_askprice": "494.95",
    "ce_askqty": "150",
    "ce_bidprice": "490.80",
    "ce_bidqty": "75",
    "ce_chng_in_oi": "7725",
    "ce_iv": "101.25",
    "ce_ltp": "497.40",
    "ce_net_chng": "29.05",
    "ce_oi": "469575",
    "ce_volume": "10123",
    "pe_askprice": "339.95",
    "pe_askqty": "75",
    "pe_bidprice": "339.15",
    "pe_bidqty": "75",
    "pe_chng_in_oi": "146175",
    "pe_iv": "109.66",
    "pe_ltp": "340.05",
    "pe_net_chng": "-13.80",
    "pe_oi": "818175",
    "pe_volume": "89466",
    "spot_price": "8683",
    "strike_price": "8500",
    "time": "1225"
  },
  {
    "ce_askprice": "501.55",
    "ce_askqty": "75",
    "ce_bidprice": "497.35",
    "ce_bidqty": "150",
    "ce_chng_in_oi": "7050",
    "ce_iv": "101.25",
    "ce_ltp": "496.45",
    "ce_net_chng": "28.10",
    "ce_oi": "468900",
    "ce_volume": "10204",
    "pe_askprice": "335.45",
    "pe_askqty": "75",
    "pe_bidprice": "334.00",
    "pe_bidqty": "150",
    "pe_chng_in_oi": "145425",
    "pe_iv": "109.66",
    "pe_ltp": "334.80",
    "pe_net_chng": "-19.05",
    "pe_oi": "817425",
    "pe_volume": "89960",
    "spot_price": "8697",
    "strike_price": "8500",
    "time": "1228"
  },
  {
    "ce_askprice": "497.45",
    "ce_askqty": "150",
    "ce_bidprice": "493.90",
    "ce_bidqty": "375",
    "ce_chng_in_oi": "7050",
    "ce_iv": "101.25",
    "ce_ltp": "502.40",
    "ce_net_chng": "34.05",
    "ce_oi": "468900",
    "ce_volume": "10234",
    "pe_askprice": "340.60",
    "pe_askqty": "75",
    "pe_bidprice": "339.20",
    "pe_bidqty": "75",
    "pe_chng_in_oi": "145425",
    "pe_iv": "109.66",
    "pe_ltp": "340.10",
    "pe_net_chng": "-13.75",
    "pe_oi": "817425",
    "pe_volume": "90204",
    "spot_price": "8689",
    "strike_price": "8500",
    "time": "1231"
  },
  {
    "ce_askprice": "477.35",
    "ce_askqty": "300",
    "ce_bidprice": "473.35",
    "ce_bidqty": "75",
    "ce_chng_in_oi": "7350",
    "ce_iv": "101.25",
    "ce_ltp": "476.50",
    "ce_net_chng": "8.15",
    "ce_oi": "469200",
    "ce_volume": "10314",
    "pe_askprice": "352.05",
    "pe_askqty": "600",
    "pe_bidprice": "351.25",
    "pe_bidqty": "75",
    "pe_chng_in_oi": "148050",
    "pe_iv": "109.66",
    "pe_ltp": "352.05",
    "pe_net_chng": "-1.80",
    "pe_oi": "820050",
    "pe_volume": "90691",
    "spot_price": "8665",
    "strike_price": "8500",
    "time": "1234"
  },
  {
    "ce_askprice": "480.00",
    "ce_askqty": "150",
    "ce_bidprice": "477.00",
    "ce_bidqty": "75",
    "ce_chng_in_oi": "6750",
    "ce_iv": "101.25",
    "ce_ltp": "476.85",
    "ce_net_chng": "8.50",
    "ce_oi": "468600",
    "ce_volume": "10404",
    "pe_askprice": "356.70",
    "pe_askqty": "300",
    "pe_bidprice": "355.70",
    "pe_bidqty": "75",
    "pe_chng_in_oi": "150525",
    "pe_iv": "109.66",
    "pe_ltp": "356.65",
    "pe_net_chng": "2.80",
    "pe_oi": "822525",
    "pe_volume": "91888",
    "spot_price": "8658",
    "strike_price": "8500",
    "time": "1237"
  },
  {
    "ce_askprice": "481.50",
    "ce_askqty": "150",
    "ce_bidprice": "477.50",
    "ce_bidqty": "375",
    "ce_chng_in_oi": "6525",
    "ce_iv": "101.25",
    "ce_ltp": "481.45",
    "ce_net_chng": "13.10",
    "ce_oi": "468375",
    "ce_volume": "10495",
    "pe_askprice": "355.00",
    "pe_askqty": "300",
    "pe_bidprice": "353.35",
    "pe_bidqty": "75",
    "pe_chng_in_oi": "153225",
    "pe_iv": "109.66",
    "pe_ltp": "354.75",
    "pe_net_chng": "0.90",
    "pe_oi": "825225",
    "pe_volume": "92399",
    "spot_price": "8664",
    "strike_price": "8500",
    "time": "1242"
  },
  {
    "ce_askprice": "476.75",
    "ce_askqty": "150",
    "ce_bidprice": "473.25",
    "ce_bidqty": "150",
    "ce_chng_in_oi": "8625",
    "ce_iv": "101.25",
    "ce_ltp": "474.15",
    "ce_net_chng": "5.80",
    "ce_oi": "470475",
    "ce_volume": "10566",
    "pe_askprice": "360.20",
    "pe_askqty": "75",
    "pe_bidprice": "358.65",
    "pe_bidqty": "75",
    "pe_chng_in_oi": "155925",
    "pe_iv": "109.66",
    "pe_ltp": "359.25",
    "pe_net_chng": "5.40",
    "pe_oi": "827925",
    "pe_volume": "93270",
    "spot_price": "8651",
    "strike_price": "8500",
    "time": "1244"
  },
  {
    "ce_askprice": "478.95",
    "ce_askqty": "75",
    "ce_bidprice": "477.05",
    "ce_bidqty": "75",
    "ce_chng_in_oi": "8475",
    "ce_iv": "101.25",
    "ce_ltp": "477.25",
    "ce_net_chng": "8.90",
    "ce_oi": "470325",
    "ce_volume": "10684",
    "pe_askprice": "361.50",
    "pe_askqty": "75",
    "pe_bidprice": "360.15",
    "pe_bidqty": "75",
    "pe_chng_in_oi": "156075",
    "pe_iv": "109.66",
    "pe_ltp": "360.95",
    "pe_net_chng": "7.10",
    "pe_oi": "828075",
    "pe_volume": "94340",
    "spot_price": "8651",
    "strike_price": "8500",
    "time": "1247"
  },
  {
    "ce_askprice": "470.50",
    "ce_askqty": "75",
    "ce_bidprice": "467.00",
    "ce_bidqty": "150",
    "ce_chng_in_oi": "10125",
    "ce_iv": "101.25",
    "ce_ltp": "468.00",
    "ce_net_chng": "-0.35",
    "ce_oi": "471975",
    "ce_volume": "10700",
    "pe_askprice": "372.50",
    "pe_askqty": "150",
    "pe_bidprice": "369.90",
    "pe_bidqty": "75",
    "pe_chng_in_oi": "160800",
    "pe_iv": "109.66",
    "pe_ltp": "372.55",
    "pe_net_chng": "18.70",
    "pe_oi": "832800",
    "pe_volume": "94651",
    "spot_price": "8643",
    "strike_price": "8500",
    "time": "1249"
  },
  {
    "ce_askprice": "468.60",
    "ce_askqty": "225",
    "ce_bidprice": "465.55",
    "ce_bidqty": "75",
    "ce_chng_in_oi": "16350",
    "ce_iv": "101.25",
    "ce_ltp": "467.45",
    "ce_net_chng": "-0.90",
    "ce_oi": "478200",
    "ce_volume": "10904",
    "pe_askprice": "370.00",
    "pe_askqty": "525",
    "pe_bidprice": "369.25",
    "pe_bidqty": "75",
    "pe_chng_in_oi": "161850",
    "pe_iv": "109.66",
    "pe_ltp": "370.00",
    "pe_net_chng": "16.15",
    "pe_oi": "833850",
    "pe_volume": "95810",
    "spot_price": "8637",
    "strike_price": "8500",
    "time": "1253"
  },
  {
    "ce_askprice": "461.15",
    "ce_askqty": "75",
    "ce_bidprice": "458.05",
    "ce_bidqty": "75",
    "ce_chng_in_oi": "16350",
    "ce_iv": "101.25",
    "ce_ltp": "461.10",
    "ce_net_chng": "-7.25",
    "ce_oi": "478200",
    "ce_volume": "10940",
    "pe_askprice": "375.10",
    "pe_askqty": "75",
    "pe_bidprice": "373.95",
    "pe_bidqty": "75",
    "pe_chng_in_oi": "161850",
    "pe_iv": "109.66",
    "pe_ltp": "375.00",
    "pe_net_chng": "21.15",
    "pe_oi": "833850",
    "pe_volume": "96291",
    "spot_price": "8636",
    "strike_price": "8500",
    "time": "1255"
  },
  {
    "ce_askprice": "470.50",
    "ce_askqty": "75",
    "ce_bidprice": "468.05",
    "ce_bidqty": "75",
    "ce_chng_in_oi": "15900",
    "ce_iv": "101.25",
    "ce_ltp": "467.00",
    "ce_net_chng": "-1.35",
    "ce_oi": "477750",
    "ce_volume": "11104",
    "pe_askprice": "368.35",
    "pe_askqty": "75",
    "pe_bidprice": "366.90",
    "pe_bidqty": "225",
    "pe_chng_in_oi": "157800",
    "pe_iv": "109.66",
    "pe_ltp": "368.00",
    "pe_net_chng": "14.15",
    "pe_oi": "829800",
    "pe_volume": "97532",
    "spot_price": "8631",
    "strike_price": "8500",
    "time": "1258"
  },
  {
    "ce_askprice": "460.75",
    "ce_askqty": "75",
    "ce_bidprice": "458.10",
    "ce_bidqty": "75",
    "ce_chng_in_oi": "15900",
    "ce_iv": "101.25",
    "ce_ltp": "458.50",
    "ce_net_chng": "-9.85",
    "ce_oi": "477750",
    "ce_volume": "11284",
    "pe_askprice": "371.90",
    "pe_askqty": "75",
    "pe_bidprice": "370.50",
    "pe_bidqty": "75",
    "pe_chng_in_oi": "157800",
    "pe_iv": "109.66",
    "pe_ltp": "370.50",
    "pe_net_chng": "16.65",
    "pe_oi": "829800",
    "pe_volume": "98108",
    "spot_price": "8624",
    "strike_price": "8500",
    "time": "1301"
  },
  {
    "ce_askprice": "457.15",
    "ce_askqty": "75",
    "ce_bidprice": "454.05",
    "ce_bidqty": "75",
    "ce_chng_in_oi": "19500",
    "ce_iv": "101.25",
    "ce_ltp": "456.25",
    "ce_net_chng": "-12.10",
    "ce_oi": "481350",
    "ce_volume": "11353",
    "pe_askprice": "374.70",
    "pe_askqty": "150",
    "pe_bidprice": "373.65",
    "pe_bidqty": "75",
    "pe_chng_in_oi": "156375",
    "pe_iv": "109.66",
    "pe_ltp": "373.60",
    "pe_net_chng": "19.75",
    "pe_oi": "828375",
    "pe_volume": "98736",
    "spot_price": "8622",
    "strike_price": "8500",
    "time": "1304"
  },
  {
    "ce_askprice": "441.80",
    "ce_askqty": "150",
    "ce_bidprice": "440.00",
    "ce_bidqty": "75",
    "ce_chng_in_oi": "20325",
    "ce_iv": "101.25",
    "ce_ltp": "444.50",
    "ce_net_chng": "-23.85",
    "ce_oi": "482175",
    "ce_volume": "11465",
    "pe_askprice": "382.50",
    "pe_askqty": "750",
    "pe_bidprice": "381.85",
    "pe_bidqty": "75",
    "pe_chng_in_oi": "153825",
    "pe_iv": "109.66",
    "pe_ltp": "382.35",
    "pe_net_chng": "28.50",
    "pe_oi": "825825",
    "pe_volume": "99571",
    "spot_price": "8599",
    "strike_price": "8500",
    "time": "1307"
  },
  {
    "ce_askprice": "437.85",
    "ce_askqty": "300",
    "ce_bidprice": "435.75",
    "ce_bidqty": "75",
    "ce_chng_in_oi": "22725",
    "ce_iv": "101.25",
    "ce_ltp": "433.90",
    "ce_net_chng": "-34.45",
    "ce_oi": "484575",
    "ce_volume": "11701",
    "pe_askprice": "387.60",
    "pe_askqty": "450",
    "pe_bidprice": "385.90",
    "pe_bidqty": "75",
    "pe_chng_in_oi": "154125",
    "pe_iv": "109.66",
    "pe_ltp": "387.35",
    "pe_net_chng": "33.50",
    "pe_oi": "826125",
    "pe_volume": "100679",
    "spot_price": "8592",
    "strike_price": "8500",
    "time": "1310"
  },
  {
    "ce_askprice": "443.40",
    "ce_askqty": "75",
    "ce_bidprice": "440.40",
    "ce_bidqty": "75",
    "ce_chng_in_oi": "39525",
    "ce_iv": "101.25",
    "ce_ltp": "442.00",
    "ce_net_chng": "-26.35",
    "ce_oi": "501375",
    "ce_volume": "12253",
    "pe_askprice": "378.20",
    "pe_askqty": "75",
    "pe_bidprice": "376.65",
    "pe_bidqty": "75",
    "pe_chng_in_oi": "154725",
    "pe_iv": "109.66",
    "pe_ltp": "378.25",
    "pe_net_chng": "24.40",
    "pe_oi": "826725",
    "pe_volume": "102834",
    "spot_price": "8608",
    "strike_price": "8500",
    "time": "1313"
  },
  {
    "ce_askprice": "448.20",
    "ce_askqty": "75",
    "ce_bidprice": "445.40",
    "ce_bidqty": "75",
    "ce_chng_in_oi": "39525",
    "ce_iv": "101.25",
    "ce_ltp": "447.75",
    "ce_net_chng": "-20.60",
    "ce_oi": "501375",
    "ce_volume": "12287",
    "pe_askprice": "373.80",
    "pe_askqty": "75",
    "pe_bidprice": "372.40",
    "pe_bidqty": "75",
    "pe_chng_in_oi": "154725",
    "pe_iv": "109.66",
    "pe_ltp": "373.75",
    "pe_net_chng": "19.90",
    "pe_oi": "826725",
    "pe_volume": "102955",
    "spot_price": "8614",
    "strike_price": "8500",
    "time": "1316"
  },
  {
    "ce_askprice": "439.00",
    "ce_askqty": "75",
    "ce_bidprice": "436.50",
    "ce_bidqty": "150",
    "ce_chng_in_oi": "39600",
    "ce_iv": "101.25",
    "ce_ltp": "438.25",
    "ce_net_chng": "-30.10",
    "ce_oi": "501450",
    "ce_volume": "12526",
    "pe_askprice": "388.00",
    "pe_askqty": "300",
    "pe_bidprice": "386.85",
    "pe_bidqty": "300",
    "pe_chng_in_oi": "153075",
    "pe_iv": "109.66",
    "pe_ltp": "387.00",
    "pe_net_chng": "33.15",
    "pe_oi": "825075",
    "pe_volume": "104193",
    "spot_price": "8592",
    "strike_price": "8500",
    "time": "1319"
  },
  {
    "ce_askprice": "436.35",
    "ce_askqty": "75",
    "ce_bidprice": "433.65",
    "ce_bidqty": "75",
    "ce_chng_in_oi": "43725",
    "ce_iv": "101.25",
    "ce_ltp": "431.60",
    "ce_net_chng": "-36.75",
    "ce_oi": "505575",
    "ce_volume": "12588",
    "pe_askprice": "387.00",
    "pe_askqty": "75",
    "pe_bidprice": "386.00",
    "pe_bidqty": "75",
    "pe_chng_in_oi": "155700",
    "pe_iv": "109.66",
    "pe_ltp": "386.25",
    "pe_net_chng": "32.40",
    "pe_oi": "827700",
    "pe_volume": "104638",
    "spot_price": "8590",
    "strike_price": "8500",
    "time": "1322"
  },
  {
    "ce_askprice": "416.10",
    "ce_askqty": "75",
    "ce_bidprice": "414.00",
    "ce_bidqty": "75",
    "ce_chng_in_oi": "43125",
    "ce_iv": "101.25",
    "ce_ltp": "416.05",
    "ce_net_chng": "-52.30",
    "ce_oi": "504975",
    "ce_volume": "13050",
    "pe_askprice": "392.40",
    "pe_askqty": "75",
    "pe_bidprice": "391.10",
    "pe_bidqty": "75",
    "pe_chng_in_oi": "156900",
    "pe_iv": "109.66",
    "pe_ltp": "391.90",
    "pe_net_chng": "38.05",
    "pe_oi": "828900",
    "pe_volume": "106527",
    "spot_price": "8568",
    "strike_price": "8500",
    "time": "1325"
  },
  {
    "ce_askprice": "388.45",
    "ce_askqty": "300",
    "ce_bidprice": "386.05",
    "ce_bidqty": "75",
    "ce_chng_in_oi": "46650",
    "ce_iv": "101.25",
    "ce_ltp": "388.45",
    "ce_net_chng": "-79.90",
    "ce_oi": "508500",
    "ce_volume": "13670",
    "pe_askprice": "402.00",
    "pe_askqty": "750",
    "pe_bidprice": "401.10",
    "pe_bidqty": "150",
    "pe_chng_in_oi": "169425",
    "pe_iv": "109.66",
    "pe_ltp": "402.00",
    "pe_net_chng": "48.15",
    "pe_oi": "841425",
    "pe_volume": "108049",
    "spot_price": "8531",
    "strike_price": "8500",
    "time": "1329"
  },
  {
    "ce_askprice": "398.85",
    "ce_askqty": "75",
    "ce_bidprice": "396.75",
    "ce_bidqty": "75",
    "ce_chng_in_oi": "67425",
    "ce_iv": "101.25",
    "ce_ltp": "399.65",
    "ce_net_chng": "-68.70",
    "ce_oi": "529275",
    "ce_volume": "13975",
    "pe_askprice": "386.05",
    "pe_askqty": "150",
    "pe_bidprice": "385.00",
    "pe_bidqty": "225",
    "pe_chng_in_oi": "171975",
    "pe_iv": "109.66",
    "pe_ltp": "386.05",
    "pe_net_chng": "32.20",
    "pe_oi": "843975",
    "pe_volume": "109354",
    "spot_price": "8565",
    "strike_price": "8500",
    "time": "1331"
  },
  {
    "ce_askprice": "392.80",
    "ce_askqty": "75",
    "ce_bidprice": "390.00",
    "ce_bidqty": "75",
    "ce_chng_in_oi": "67650",
    "ce_iv": "101.25",
    "ce_ltp": "391.80",
    "ce_net_chng": "-76.55",
    "ce_oi": "529500",
    "ce_volume": "14485",
    "pe_askprice": "398.20",
    "pe_askqty": "75",
    "pe_bidprice": "396.75",
    "pe_bidqty": "75",
    "pe_chng_in_oi": "170700",
    "pe_iv": "109.66",
    "pe_ltp": "398.00",
    "pe_net_chng": "44.15",
    "pe_oi": "842700",
    "pe_volume": "110840",
    "spot_price": "8552",
    "strike_price": "8500",
    "time": "1334"
  },
  {
    "ce_askprice": "435.90",
    "ce_askqty": "375",
    "ce_bidprice": "432.60",
    "ce_bidqty": "75",
    "ce_chng_in_oi": "72750",
    "ce_iv": "101.25",
    "ce_ltp": "432.50",
    "ce_net_chng": "-35.85",
    "ce_oi": "534600",
    "ce_volume": "15050",
    "pe_askprice": "363.60",
    "pe_askqty": "75",
    "pe_bidprice": "362.20",
    "pe_bidqty": "750",
    "pe_chng_in_oi": "174000",
    "pe_iv": "109.66",
    "pe_ltp": "363.60",
    "pe_net_chng": "9.75",
    "pe_oi": "846000",
    "pe_volume": "112545",
    "spot_price": "8623",
    "strike_price": "8500",
    "time": "1337"
  },
  {
    "ce_askprice": "429.00",
    "ce_askqty": "150",
    "ce_bidprice": "426.00",
    "ce_bidqty": "75",
    "ce_chng_in_oi": "74700",
    "ce_iv": "101.25",
    "ce_ltp": "429.00",
    "ce_net_chng": "-39.35",
    "ce_oi": "536550",
    "ce_volume": "15595",
    "pe_askprice": "371.65",
    "pe_askqty": "75",
    "pe_bidprice": "370.15",
    "pe_bidqty": "75",
    "pe_chng_in_oi": "191700",
    "pe_iv": "109.66",
    "pe_ltp": "371.70",
    "pe_net_chng": "17.85",
    "pe_oi": "863700",
    "pe_volume": "114268",
    "spot_price": "8621",
    "strike_price": "8500",
    "time": "1341"
  },
  {
    "ce_askprice": "444.50",
    "ce_askqty": "150",
    "ce_bidprice": "440.90",
    "ce_bidqty": "150",
    "ce_chng_in_oi": "74700",
    "ce_iv": "101.25",
    "ce_ltp": "443.00",
    "ce_net_chng": "-25.35",
    "ce_oi": "536550",
    "ce_volume": "15687",
    "pe_askprice": "361.75",
    "pe_askqty": "75",
    "pe_bidprice": "360.25",
    "pe_bidqty": "75",
    "pe_chng_in_oi": "191700",
    "pe_iv": "109.66",
    "pe_ltp": "361.75",
    "pe_net_chng": "7.90",
    "pe_oi": "863700",
    "pe_volume": "114879",
    "spot_price": "8646",
    "strike_price": "8500",
    "time": "1343"
  },
  {
    "ce_askprice": "448.00",
    "ce_askqty": "75",
    "ce_bidprice": "445.10",
    "ce_bidqty": "150",
    "ce_chng_in_oi": "75900",
    "ce_iv": "101.25",
    "ce_ltp": "446.75",
    "ce_net_chng": "-21.60",
    "ce_oi": "537750",
    "ce_volume": "16018",
    "pe_askprice": "351.00",
    "pe_askqty": "1575",
    "pe_bidprice": "349.65",
    "pe_bidqty": "75",
    "pe_chng_in_oi": "190950",
    "pe_iv": "109.66",
    "pe_ltp": "351.30",
    "pe_net_chng": "-2.55",
    "pe_oi": "862950",
    "pe_volume": "116585",
    "spot_price": "8664",
    "strike_price": "8500",
    "time": "1346"
  },
  {
    "ce_askprice": "453.70",
    "ce_askqty": "150",
    "ce_bidprice": "450.05",
    "ce_bidqty": "300",
    "ce_chng_in_oi": "79500",
    "ce_iv": "101.25",
    "ce_ltp": "447.10",
    "ce_net_chng": "-21.25",
    "ce_oi": "541350",
    "ce_volume": "16082",
    "pe_askprice": "349.70",
    "pe_askqty": "150",
    "pe_bidprice": "348.65",
    "pe_bidqty": "75",
    "pe_chng_in_oi": "188850",
    "pe_iv": "109.66",
    "pe_ltp": "349.55",
    "pe_net_chng": "-4.30",
    "pe_oi": "860850",
    "pe_volume": "117041",
    "spot_price": "8676",
    "strike_price": "8500",
    "time": "1349"
  },
  {
    "ce_askprice": "458.35",
    "ce_askqty": "75",
    "ce_bidprice": "455.90",
    "ce_bidqty": "150",
    "ce_chng_in_oi": "76575",
    "ce_iv": "101.25",
    "ce_ltp": "460.55",
    "ce_net_chng": "-7.80",
    "ce_oi": "538425",
    "ce_volume": "16345",
    "pe_askprice": "345.75",
    "pe_askqty": "75",
    "pe_bidprice": "344.80",
    "pe_bidqty": "75",
    "pe_chng_in_oi": "194550",
    "pe_iv": "109.66",
    "pe_ltp": "344.60",
    "pe_net_chng": "-9.25",
    "pe_oi": "866550",
    "pe_volume": "118701",
    "spot_price": "8682",
    "strike_price": "8500",
    "time": "1353"
  },
  {
    "ce_askprice": "468.90",
    "ce_askqty": "450",
    "ce_bidprice": "464.70",
    "ce_bidqty": "225",
    "ce_chng_in_oi": "77475",
    "ce_iv": "101.25",
    "ce_ltp": "465.50",
    "ce_net_chng": "-2.85",
    "ce_oi": "539325",
    "ce_volume": "16457",
    "pe_askprice": "341.20",
    "pe_askqty": "75",
    "pe_bidprice": "340.00",
    "pe_bidqty": "2850",
    "pe_chng_in_oi": "198150",
    "pe_iv": "109.66",
    "pe_ltp": "340.05",
    "pe_net_chng": "-13.80",
    "pe_oi": "870150",
    "pe_volume": "119144",
    "spot_price": "8700",
    "strike_price": "8500",
    "time": "1355"
  },
  {
    "ce_askprice": "459.95",
    "ce_askqty": "75",
    "ce_bidprice": "456.45",
    "ce_bidqty": "225",
    "ce_chng_in_oi": "82725",
    "ce_iv": "101.25",
    "ce_ltp": "459.85",
    "ce_net_chng": "-8.50",
    "ce_oi": "544575",
    "ce_volume": "16703",
    "pe_askprice": "356.80",
    "pe_askqty": "150",
    "pe_bidprice": "355.75",
    "pe_bidqty": "75",
    "pe_chng_in_oi": "201750",
    "pe_iv": "109.66",
    "pe_ltp": "355.60",
    "pe_net_chng": "1.75",
    "pe_oi": "873750",
    "pe_volume": "120437",
    "spot_price": "8671",
    "strike_price": "8500",
    "time": "1358"
  },
  {
    "ce_askprice": "464.65",
    "ce_askqty": "75",
    "ce_bidprice": "460.25",
    "ce_bidqty": "225",
    "ce_chng_in_oi": "77475",
    "ce_iv": "101.25",
    "ce_ltp": "461.75",
    "ce_net_chng": "-6.60",
    "ce_oi": "539325",
    "ce_volume": "16398",
    "pe_askprice": "343.60",
    "pe_askqty": "75",
    "pe_bidprice": "342.65",
    "pe_bidqty": "75",
    "pe_chng_in_oi": "198150",
    "pe_iv": "109.66",
    "pe_ltp": "343.30",
    "pe_net_chng": "-10.55",
    "pe_oi": "870150",
    "pe_volume": "119017",
    "spot_price": "8694",
    "strike_price": "8500",
    "time": "1401"
  },
  {
    "ce_askprice": "483.35",
    "ce_askqty": "225",
    "ce_bidprice": "480.05",
    "ce_bidqty": "150",
    "ce_chng_in_oi": "78675",
    "ce_iv": "101.25",
    "ce_ltp": "480.15",
    "ce_net_chng": "11.80",
    "ce_oi": "540525",
    "ce_volume": "17032",
    "pe_askprice": "342.10",
    "pe_askqty": "525",
    "pe_bidprice": "340.85",
    "pe_bidqty": "75",
    "pe_chng_in_oi": "203625",
    "pe_iv": "109.66",
    "pe_ltp": "341.25",
    "pe_net_chng": "-12.60",
    "pe_oi": "875625",
    "pe_volume": "122010",
    "spot_price": "8719",
    "strike_price": "8500",
    "time": "1405"
  },
  {
    "ce_askprice": "469.65",
    "ce_askqty": "225",
    "ce_bidprice": "466.50",
    "ce_bidqty": "150",
    "ce_chng_in_oi": "79275",
    "ce_iv": "101.25",
    "ce_ltp": "466.65",
    "ce_net_chng": "-1.70",
    "ce_oi": "541125",
    "ce_volume": "17112",
    "pe_askprice": "348.40",
    "pe_askqty": "75",
    "pe_bidprice": "347.25",
    "pe_bidqty": "75",
    "pe_chng_in_oi": "206100",
    "pe_iv": "109.66",
    "pe_ltp": "348.35",
    "pe_net_chng": "-5.50",
    "pe_oi": "878100",
    "pe_volume": "122698",
    "spot_price": "8702",
    "strike_price": "8500",
    "time": "1407"
  },
  {
    "ce_askprice": "487.70",
    "ce_askqty": "150",
    "ce_bidprice": "483.65",
    "ce_bidqty": "75",
    "ce_chng_in_oi": "80025",
    "ce_iv": "101.25",
    "ce_ltp": "482.90",
    "ce_net_chng": "14.55",
    "ce_oi": "541875",
    "ce_volume": "17202",
    "pe_askprice": "341.30",
    "pe_askqty": "75",
    "pe_bidprice": "340.10",
    "pe_bidqty": "150",
    "pe_chng_in_oi": "207150",
    "pe_iv": "109.66",
    "pe_ltp": "340.85",
    "pe_net_chng": "-13.00",
    "pe_oi": "879150",
    "pe_volume": "123230",
    "spot_price": "8723",
    "strike_price": "8500",
    "time": "1410"
  },
  {
    "ce_askprice": "511.45",
    "ce_askqty": "75",
    "ce_bidprice": "506.85",
    "ce_bidqty": "150",
    "ce_chng_in_oi": "80025",
    "ce_iv": "101.25",
    "ce_ltp": "506.85",
    "ce_net_chng": "38.50",
    "ce_oi": "541875",
    "ce_volume": "17378",
    "pe_askprice": "326.10",
    "pe_askqty": "150",
    "pe_bidprice": "325.25",
    "pe_bidqty": "75",
    "pe_chng_in_oi": "207150",
    "pe_iv": "109.66",
    "pe_ltp": "326.05",
    "pe_net_chng": "-27.80",
    "pe_oi": "879150",
    "pe_volume": "124143",
    "spot_price": "8756",
    "strike_price": "8500",
    "time": "1413"
  },
  {
    "ce_askprice": "511.00",
    "ce_askqty": "75",
    "ce_bidprice": "507.75",
    "ce_bidqty": "150",
    "ce_chng_in_oi": "66825",
    "ce_iv": "101.25",
    "ce_ltp": "509.20",
    "ce_net_chng": "40.85",
    "ce_oi": "528675",
    "ce_volume": "17722",
    "pe_askprice": "323.10",
    "pe_askqty": "75",
    "pe_bidprice": "321.55",
    "pe_bidqty": "75",
    "pe_chng_in_oi": "212175",
    "pe_iv": "109.66",
    "pe_ltp": "323.35",
    "pe_net_chng": "-30.50",
    "pe_oi": "884175",
    "pe_volume": "125348",
    "spot_price": "8768",
    "strike_price": "8500",
    "time": "1416"
  },
  {
    "ce_askprice": "519.90",
    "ce_askqty": "75",
    "ce_bidprice": "516.65",
    "ce_bidqty": "150",
    "ce_chng_in_oi": "66825",
    "ce_iv": "101.25",
    "ce_ltp": "515.80",
    "ce_net_chng": "47.45",
    "ce_oi": "528675",
    "ce_volume": "17807",
    "pe_askprice": "314.50",
    "pe_askqty": "225",
    "pe_bidprice": "313.20",
    "pe_bidqty": "75",
    "pe_chng_in_oi": "212175",
    "pe_iv": "109.66",
    "pe_ltp": "314.15",
    "pe_net_chng": "-39.70",
    "pe_oi": "884175",
    "pe_volume": "126098",
    "spot_price": "8787",
    "strike_price": "8500",
    "time": "1419"
  },
  {
    "ce_askprice": "524.45",
    "ce_askqty": "150",
    "ce_bidprice": "520.05",
    "ce_bidqty": "75",
    "ce_chng_in_oi": "65475",
    "ce_iv": "101.25",
    "ce_ltp": "523.20",
    "ce_net_chng": "54.85",
    "ce_oi": "527325",
    "ce_volume": "17926",
    "pe_askprice": "304.00",
    "pe_askqty": "375",
    "pe_bidprice": "302.95",
    "pe_bidqty": "150",
    "pe_chng_in_oi": "212100",
    "pe_iv": "109.66",
    "pe_ltp": "303.15",
    "pe_net_chng": "-50.70",
    "pe_oi": "884100",
    "pe_volume": "127777",
    "spot_price": "8808",
    "strike_price": "8500",
    "time": "1422"
  },
  {
    "ce_askprice": "499.45",
    "ce_askqty": "225",
    "ce_bidprice": "494.75",
    "ce_bidqty": "75",
    "ce_chng_in_oi": "60300",
    "ce_iv": "101.25",
    "ce_ltp": "495.35",
    "ce_net_chng": "27.00",
    "ce_oi": "522150",
    "ce_volume": "18165",
    "pe_askprice": "322.25",
    "pe_askqty": "75",
    "pe_bidprice": "321.25",
    "pe_bidqty": "225",
    "pe_chng_in_oi": "215250",
    "pe_iv": "109.66",
    "pe_ltp": "321.05",
    "pe_net_chng": "-32.80",
    "pe_oi": "887250",
    "pe_volume": "129340",
    "spot_price": "8768",
    "strike_price": "8500",
    "time": "1425"
  },
  {
    "ce_askprice": "507.75",
    "ce_askqty": "150",
    "ce_bidprice": "503.80",
    "ce_bidqty": "75",
    "ce_chng_in_oi": "60300",
    "ce_iv": "101.25",
    "ce_ltp": "509.80",
    "ce_net_chng": "41.45",
    "ce_oi": "522150",
    "ce_volume": "18192",
    "pe_askprice": "313.65",
    "pe_askqty": "75",
    "pe_bidprice": "312.40",
    "pe_bidqty": "300",
    "pe_chng_in_oi": "215250",
    "pe_iv": "109.66",
    "pe_ltp": "314.25",
    "pe_net_chng": "-39.60",
    "pe_oi": "887250",
    "pe_volume": "129808",
    "spot_price": "8786",
    "strike_price": "8500",
    "time": "1428"
  },
  {
    "ce_askprice": "529.75",
    "ce_askqty": "150",
    "ce_bidprice": "524.05",
    "ce_bidqty": "75",
    "ce_chng_in_oi": "60825",
    "ce_iv": "101.25",
    "ce_ltp": "528.80",
    "ce_net_chng": "60.45",
    "ce_oi": "522675",
    "ce_volume": "18404",
    "pe_askprice": "289.35",
    "pe_askqty": "75",
    "pe_bidprice": "288.65",
    "pe_bidqty": "75",
    "pe_chng_in_oi": "219150",
    "pe_iv": "109.66",
    "pe_ltp": "288.60",
    "pe_net_chng": "-65.25",
    "pe_oi": "891150",
    "pe_volume": "131431",
    "spot_price": "8826",
    "strike_price": "8500",
    "time": "1431"
  },
  {
    "ce_askprice": "511.00",
    "ce_askqty": "75",
    "ce_bidprice": "506.50",
    "ce_bidqty": "75",
    "ce_chng_in_oi": "61875",
    "ce_iv": "101.25",
    "ce_ltp": "517.50",
    "ce_net_chng": "49.15",
    "ce_oi": "523725",
    "ce_volume": "18527",
    "pe_askprice": "300.00",
    "pe_askqty": "2250",
    "pe_bidprice": "299.20",
    "pe_bidqty": "75",
    "pe_chng_in_oi": "223725",
    "pe_iv": "109.66",
    "pe_ltp": "299.25",
    "pe_net_chng": "-54.60",
    "pe_oi": "895725",
    "pe_volume": "132496",
    "spot_price": "8802",
    "strike_price": "8500",
    "time": "1434"
  },
  {
    "ce_askprice": "466.95",
    "ce_askqty": "150",
    "ce_bidprice": "462.85",
    "ce_bidqty": "150",
    "ce_chng_in_oi": "60075",
    "ce_iv": "101.25",
    "ce_ltp": "467.60",
    "ce_net_chng": "-0.75",
    "ce_oi": "521925",
    "ce_volume": "18858",
    "pe_askprice": "331.90",
    "pe_askqty": "75",
    "pe_bidprice": "330.65",
    "pe_bidqty": "150",
    "pe_chng_in_oi": "221400",
    "pe_iv": "109.66",
    "pe_ltp": "330.70",
    "pe_net_chng": "-23.15",
    "pe_oi": "893400",
    "pe_volume": "135135",
    "spot_price": "8708",
    "strike_price": "8500",
    "time": "1437"
  },
  {
    "ce_askprice": "460.55",
    "ce_askqty": "150",
    "ce_bidprice": "455.90",
    "ce_bidqty": "75",
    "ce_chng_in_oi": "50700",
    "ce_iv": "101.25",
    "ce_ltp": "462.05",
    "ce_net_chng": "-6.30",
    "ce_oi": "512550",
    "ce_volume": "18994",
    "pe_askprice": "341.60",
    "pe_askqty": "75",
    "pe_bidprice": "340.70",
    "pe_bidqty": "75",
    "pe_chng_in_oi": "220725",
    "pe_iv": "109.66",
    "pe_ltp": "340.35",
    "pe_net_chng": "-13.50",
    "pe_oi": "892725",
    "pe_volume": "137247",
    "spot_price": "8683",
    "strike_price": "8500",
    "time": "1440"
  },
  {
    "ce_askprice": "465.70",
    "ce_askqty": "75",
    "ce_bidprice": "462.70",
    "ce_bidqty": "75",
    "ce_chng_in_oi": "52050",
    "ce_iv": "101.25",
    "ce_ltp": "462.70",
    "ce_net_chng": "-5.65",
    "ce_oi": "513900",
    "ce_volume": "19077",
    "pe_askprice": "348.45",
    "pe_askqty": "75",
    "pe_bidprice": "347.20",
    "pe_bidqty": "75",
    "pe_chng_in_oi": "221025",
    "pe_iv": "109.66",
    "pe_ltp": "347.25",
    "pe_net_chng": "-6.60",
    "pe_oi": "893025",
    "pe_volume": "138340",
    "spot_price": "8687",
    "strike_price": "8500",
    "time": "1443"
  },
  {
    "ce_askprice": "450.00",
    "ce_askqty": "150",
    "ce_bidprice": "446.30",
    "ce_bidqty": "450",
    "ce_chng_in_oi": "51525",
    "ce_iv": "101.25",
    "ce_ltp": "449.75",
    "ce_net_chng": "-18.60",
    "ce_oi": "513375",
    "ce_volume": "19194",
    "pe_askprice": "352.90",
    "pe_askqty": "75",
    "pe_bidprice": "351.35",
    "pe_bidqty": "75",
    "pe_chng_in_oi": "228600",
    "pe_iv": "109.66",
    "pe_ltp": "351.65",
    "pe_net_chng": "-2.20",
    "pe_oi": "900600",
    "pe_volume": "140067",
    "spot_price": "8670",
    "strike_price": "8500",
    "time": "1446"
  },
  {
    "ce_askprice": "461.95",
    "ce_askqty": "300",
    "ce_bidprice": "457.85",
    "ce_bidqty": "75",
    "ce_chng_in_oi": "51150",
    "ce_iv": "101.25",
    "ce_ltp": "457.95",
    "ce_net_chng": "-10.40",
    "ce_oi": "513000",
    "ce_volume": "19223",
    "pe_askprice": "342.70",
    "pe_askqty": "75",
    "pe_bidprice": "341.30",
    "pe_bidqty": "150",
    "pe_chng_in_oi": "223350",
    "pe_iv": "109.66",
    "pe_ltp": "342.05",
    "pe_net_chng": "-11.80",
    "pe_oi": "895350",
    "pe_volume": "140423",
    "spot_price": "8686",
    "strike_price": "8500",
    "time": "1449"
  },
  {
    "ce_askprice": "440.40",
    "ce_askqty": "75",
    "ce_bidprice": "436.70",
    "ce_bidqty": "225",
    "ce_chng_in_oi": "54450",
    "ce_iv": "101.25",
    "ce_ltp": "442.60",
    "ce_net_chng": "-25.75",
    "ce_oi": "516300",
    "ce_volume": "19499",
    "pe_askprice": "351.30",
    "pe_askqty": "375",
    "pe_bidprice": "350.00",
    "pe_bidqty": "75",
    "pe_chng_in_oi": "220875",
    "pe_iv": "109.66",
    "pe_ltp": "350.35",
    "pe_net_chng": "-3.50",
    "pe_oi": "892875",
    "pe_volume": "142671",
    "spot_price": "8661",
    "strike_price": "8500",
    "time": "1452"
  },
  {
    "ce_askprice": "442.65",
    "ce_askqty": "225",
    "ce_bidprice": "439.05",
    "ce_bidqty": "75",
    "ce_chng_in_oi": "52725",
    "ce_iv": "101.25",
    "ce_ltp": "441.70",
    "ce_net_chng": "-26.65",
    "ce_oi": "514575",
    "ce_volume": "19635",
    "pe_askprice": "348.65",
    "pe_askqty": "75",
    "pe_bidprice": "347.70",
    "pe_bidqty": "75",
    "pe_chng_in_oi": "222600",
    "pe_iv": "109.66",
    "pe_ltp": "348.00",
    "pe_net_chng": "-5.85",
    "pe_oi": "894600",
    "pe_volume": "143358",
    "spot_price": "8659",
    "strike_price": "8500",
    "time": "1455"
  },
  {
    "ce_askprice": "464.70",
    "ce_askqty": "75",
    "ce_bidprice": "460.05",
    "ce_bidqty": "75",
    "ce_chng_in_oi": "52350",
    "ce_iv": "101.25",
    "ce_ltp": "460.45",
    "ce_net_chng": "-7.90",
    "ce_oi": "514200",
    "ce_volume": "19872",
    "pe_askprice": "318.85",
    "pe_askqty": "75",
    "pe_bidprice": "318.10",
    "pe_bidqty": "75",
    "pe_chng_in_oi": "221400",
    "pe_iv": "109.66",
    "pe_ltp": "318.00",
    "pe_net_chng": "-35.85",
    "pe_oi": "893400",
    "pe_volume": "144410",
    "spot_price": "8697",
    "strike_price": "8500",
    "time": "1458"
  },
  {
    "ce_askprice": "454.70",
    "ce_askqty": "225",
    "ce_bidprice": "450.90",
    "ce_bidqty": "375",
    "ce_chng_in_oi": "58050",
    "ce_iv": "101.25",
    "ce_ltp": "452.65",
    "ce_net_chng": "-15.70",
    "ce_oi": "519900",
    "ce_volume": "20165",
    "pe_askprice": "329.35",
    "pe_askqty": "225",
    "pe_bidprice": "327.95",
    "pe_bidqty": "150",
    "pe_chng_in_oi": "207225",
    "pe_iv": "109.66",
    "pe_ltp": "328.20",
    "pe_net_chng": "-25.65",
    "pe_oi": "879225",
    "pe_volume": "145578",
    "spot_price": "8680",
    "strike_price": "8500",
    "time": "1501"
  },
  {
    "ce_askprice": "424.95",
    "ce_askqty": "225",
    "ce_bidprice": "421.35",
    "ce_bidqty": "300",
    "ce_chng_in_oi": "60675",
    "ce_iv": "101.25",
    "ce_ltp": "425.05",
    "ce_net_chng": "-43.30",
    "ce_oi": "522525",
    "ce_volume": "20523",
    "pe_askprice": "347.80",
    "pe_askqty": "225",
    "pe_bidprice": "346.70",
    "pe_bidqty": "75",
    "pe_chng_in_oi": "214350",
    "pe_iv": "109.66",
    "pe_ltp": "347.85",
    "pe_net_chng": "-6.00",
    "pe_oi": "886350",
    "pe_volume": "146733",
    "spot_price": "8641",
    "strike_price": "8500",
    "time": "1504"
  },
  {
    "ce_askprice": "419.65",
    "ce_askqty": "150",
    "ce_bidprice": "416.15",
    "ce_bidqty": "75",
    "ce_chng_in_oi": "59025",
    "ce_iv": "101.25",
    "ce_ltp": "416.90",
    "ce_net_chng": "-51.45",
    "ce_oi": "520875",
    "ce_volume": "20828",
    "pe_askprice": "349.45",
    "pe_askqty": "150",
    "pe_bidprice": "347.75",
    "pe_bidqty": "75",
    "pe_chng_in_oi": "212025",
    "pe_iv": "109.66",
    "pe_ltp": "349.40",
    "pe_net_chng": "-4.45",
    "pe_oi": "884025",
    "pe_volume": "148424",
    "spot_price": "8627",
    "strike_price": "8500",
    "time": "1507"
  },
  {
    "ce_askprice": "428.25",
    "ce_askqty": "75",
    "ce_bidprice": "424.95",
    "ce_bidqty": "300",
    "ce_chng_in_oi": "69450",
    "ce_iv": "101.25",
    "ce_ltp": "424.65",
    "ce_net_chng": "-43.70",
    "ce_oi": "531300",
    "ce_volume": "21416",
    "pe_askprice": "335.00",
    "pe_askqty": "150",
    "pe_bidprice": "332.75",
    "pe_bidqty": "225",
    "pe_chng_in_oi": "207225",
    "pe_iv": "109.66",
    "pe_ltp": "333.00",
    "pe_net_chng": "-20.85",
    "pe_oi": "879225",
    "pe_volume": "149609",
    "spot_price": "8633",
    "strike_price": "8500",
    "time": "1510"
  },
  {
    "ce_askprice": "430.00",
    "ce_askqty": "300",
    "ce_bidprice": "427.90",
    "ce_bidqty": "75",
    "ce_chng_in_oi": "81675",
    "ce_iv": "101.25",
    "ce_ltp": "426.50",
    "ce_net_chng": "-41.85",
    "ce_oi": "543525",
    "ce_volume": "21659",
    "pe_askprice": "330.85",
    "pe_askqty": "75",
    "pe_bidprice": "330.00",
    "pe_bidqty": "1050",
    "pe_chng_in_oi": "204825",
    "pe_iv": "109.66",
    "pe_ltp": "330.80",
    "pe_net_chng": "-23.05",
    "pe_oi": "876825",
    "pe_volume": "150670",
    "spot_price": "8645",
    "strike_price": "8500",
    "time": "1513"
  },
  {
    "ce_askprice": "438.90",
    "ce_askqty": "150",
    "ce_bidprice": "435.45",
    "ce_bidqty": "75",
    "ce_chng_in_oi": "83250",
    "ce_iv": "101.25",
    "ce_ltp": "436.85",
    "ce_net_chng": "-31.50",
    "ce_oi": "545100",
    "ce_volume": "21897",
    "pe_askprice": "322.70",
    "pe_askqty": "225",
    "pe_bidprice": "321.45",
    "pe_bidqty": "225",
    "pe_chng_in_oi": "197100",
    "pe_iv": "109.66",
    "pe_ltp": "322.50",
    "pe_net_chng": "-31.35",
    "pe_oi": "869100",
    "pe_volume": "151460",
    "spot_price": "8667",
    "strike_price": "8500",
    "time": "1516"
  },
  {
    "ce_askprice": "442.00",
    "ce_askqty": "300",
    "ce_bidprice": "440.25",
    "ce_bidqty": "150",
    "ce_chng_in_oi": "85200",
    "ce_iv": "101.25",
    "ce_ltp": "442.00",
    "ce_net_chng": "-26.35",
    "ce_oi": "547050",
    "ce_volume": "22026",
    "pe_askprice": "319.75",
    "pe_askqty": "150",
    "pe_bidprice": "318.40",
    "pe_bidqty": "375",
    "pe_chng_in_oi": "190875",
    "pe_iv": "109.66",
    "pe_ltp": "319.50",
    "pe_net_chng": "-34.35",
    "pe_oi": "862875",
    "pe_volume": "152135",
    "spot_price": "8667",
    "strike_price": "8500",
    "time": "1519"
  },
  {
    "ce_askprice": "449.95",
    "ce_askqty": "75",
    "ce_bidprice": "447.45",
    "ce_bidqty": "75",
    "ce_chng_in_oi": "91725",
    "ce_iv": "101.25",
    "ce_ltp": "449.00",
    "ce_net_chng": "-19.35",
    "ce_oi": "553575",
    "ce_volume": "22324",
    "pe_askprice": "315.80",
    "pe_askqty": "150",
    "pe_bidprice": "314.25",
    "pe_bidqty": "150",
    "pe_chng_in_oi": "186525",
    "pe_iv": "109.66",
    "pe_ltp": "315.65",
    "pe_net_chng": "-38.20",
    "pe_oi": "858525",
    "pe_volume": "153254",
    "spot_price": "8692",
    "strike_price": "8500",
    "time": "1522"
  },
  {
    "ce_askprice": "448.05",
    "ce_askqty": "75",
    "ce_bidprice": "445.10",
    "ce_bidqty": "75",
    "ce_chng_in_oi": "94725",
    "ce_iv": "101.25",
    "ce_ltp": "445.05",
    "ce_net_chng": "-23.30",
    "ce_oi": "556575",
    "ce_volume": "22499",
    "pe_askprice": "319.05",
    "pe_askqty": "75",
    "pe_bidprice": "318.15",
    "pe_bidqty": "150",
    "pe_chng_in_oi": "179775",
    "pe_iv": "109.66",
    "pe_ltp": "318.95",
    "pe_net_chng": "-34.90",
    "pe_oi": "851775",
    "pe_volume": "154183",
    "spot_price": "8671",
    "strike_price": "8500",
    "time": "1525"
  },
  {
    "ce_askprice": "447.90",
    "ce_askqty": "75",
    "ce_bidprice": "444.60",
    "ce_bidqty": "75",
    "ce_chng_in_oi": "90525",
    "ce_iv": "101.25",
    "ce_ltp": "446.20",
    "ce_net_chng": "-22.15",
    "ce_oi": "552375",
    "ce_volume": "22593",
    "pe_askprice": "324.80",
    "pe_askqty": "75",
    "pe_bidprice": "323.25",
    "pe_bidqty": "150",
    "pe_chng_in_oi": "183150",
    "pe_iv": "109.66",
    "pe_ltp": "324.75",
    "pe_net_chng": "-29.10",
    "pe_oi": "855150",
    "pe_volume": "154610",
    "spot_price": "8675",
    "strike_price": "8500",
    "time": "1527"
  },
  {
    "ce_askprice": "443.00",
    "ce_askqty": "150",
    "ce_bidprice": "442.00",
    "ce_bidqty": "1200",
    "ce_chng_in_oi": "87975",
    "ce_iv": "101.25",
    "ce_ltp": "442.95",
    "ce_net_chng": "-25.40",
    "ce_oi": "549825",
    "ce_volume": "22669",
    "pe_askprice": "323.70",
    "pe_askqty": "2100",
    "pe_bidprice": "322.50",
    "pe_bidqty": "150",
    "pe_chng_in_oi": "172575",
    "pe_iv": "109.66",
    "pe_ltp": "322.45",
    "pe_net_chng": "-31.40",
    "pe_oi": "844575",
    "pe_volume": "155074",
    "spot_price": "8676",
    "strike_price": "8500",
    "time": "1531"
  },
  {
    "ce_askprice": "452.50",
    "ce_askqty": "150",
    "ce_bidprice": "441.00",
    "ce_bidqty": "450",
    "ce_chng_in_oi": "88500",
    "ce_iv": "101.25",
    "ce_ltp": "441.00",
    "ce_net_chng": "-27.35",
    "ce_oi": "550350",
    "ce_volume": "22848",
    "pe_askprice": "322.85",
    "pe_askqty": "1125",
    "pe_bidprice": "320.00",
    "pe_bidqty": "1050",
    "pe_chng_in_oi": "178650",
    "pe_iv": "109.66",
    "pe_ltp": "320.00",
    "pe_net_chng": "-33.85",
    "pe_oi": "850650",
    "pe_volume": "155637",
    "spot_price": "8674",
    "strike_price": "8500",
    "time": "1533"
  }
]